{
  "type": "book",
  "id": "englishpod-初级-englishpod-初级-英文播客-0042",
  "title": "EnglishPod 初级 英文播客 0042",
  "totalSegments": 223,
  "seriesId": "englishpod-初级",
  "segments": [
    {
      "id": 1,
      "en": "Hello, English learners.",
      "cn": "你好，英语学习者。"
    },
    {
      "id": 2,
      "en": "Welcome back to EnglishPod.",
      "cn": "欢迎回到EnglishPod。"
    },
    {
      "id": 3,
      "en": "My name is Marco.",
      "cn": "我叫Marco。"
    },
    {
      "id": 4,
      "en": "And I'm Erica.",
      "cn": "我是Erica。"
    },
    {
      "id": 5,
      "en": "And today with Erica, we're bringing you a great lesson about time.",
      "cn": "今天和Erica一起，我们将为你带来一个关于时间的精彩课程。"
    },
    {
      "id": 6,
      "en": "You need more of it.",
      "cn": "你需要更多时间。"
    },
    {
      "id": 7,
      "en": "We need more time, right?",
      "cn": "我们需要更多时间，对吧？"
    },
    {
      "id": 8,
      "en": "So we're going to be teaching you how you can ask for more time.",
      "cn": "所以我们将教你如何请求更多时间。"
    },
    {
      "id": 9,
      "en": "If you're working on a project at work and you can't finish it on time, you have to ask your boss for more time.",
      "cn": "如果你在工作上做一个项目，无法按时完成，你必须向你的老板请求更多时间。"
    },
    {
      "id": 10,
      "en": "Right.",
      "cn": "对。"
    },
    {
      "id": 11,
      "en": "So today in our dialogue, Casey needs more time to put together a press kit.",
      "cn": "所以今天在我们的对话中，Casey需要更多时间来准备新闻资料包。"
    },
    {
      "id": 12,
      "en": "What's a press kit?",
      "cn": "什么是新闻资料包？"
    },
    {
      "id": 13,
      "en": "Good question.",
      "cn": "好问题。"
    },
    {
      "id": 14,
      "en": "A press kit is something the marketing department will put together.",
      "cn": "新闻资料包是市场部准备的东西。"
    },
    {
      "id": 15,
      "en": "Basically pictures, logos, information about the company.",
      "cn": "基本上是图片、标志、公司信息。"
    },
    {
      "id": 16,
      "en": "So when a newspaper or a magazine wants to write an article about them, so they have something already prepared that they could give the newspaper or magazine.",
      "cn": "所以当报纸或杂志想写关于他们的文章时，他们已经准备好可以给报纸或杂志的东西。"
    },
    {
      "id": 17,
      "en": "Okay.",
      "cn": "好的。"
    },
    {
      "id": 18,
      "en": "Okay.",
      "cn": "好的。"
    },
    {
      "id": 19,
      "en": "So let's listen to our dialogue for the first time.",
      "cn": "那么我们来第一次听我们的对话。"
    },
    {
      "id": 20,
      "en": "And as always, it's going to be at a normal speed, so it might be a little bit difficult to understand.",
      "cn": "和往常一样，速度会正常，所以可能有点难以理解。"
    },
    {
      "id": 21,
      "en": "We'll come back in one minute and tell you about some of the key language.",
      "cn": "我们会在一分钟后回来，告诉你一些关键语言。"
    },
    {
      "id": 22,
      "en": "So, Casey, how are things going with the photos for the press kit?",
      "cn": "所以，Casey，新闻资料包的照片进展如何？"
    },
    {
      "id": 23,
      "en": "Yeah, I've been meaning to talk to you about that.",
      "cn": "是的，我一直想和你谈谈这个。"
    },
    {
      "id": 24,
      "en": "I might need to ask for an extension on that deadline.",
      "cn": "我可能需要请求延长截止日期。"
    },
    {
      "id": 25,
      "en": "You've had over a month to get this finalized.",
      "cn": "你已经有一个多月的时间来完成这个。"
    },
    {
      "id": 26,
      "en": "Why are things delayed?",
      "cn": "为什么会延迟？"
    },
    {
      "id": 27,
      "en": "Well, the thing is, we ran into a lot of problems.",
      "cn": "嗯，问题是我们遇到了很多麻烦。"
    },
    {
      "id": 28,
      "en": "I'm not looking for excuses here.",
      "cn": "我不是在找借口。"
    },
    {
      "id": 29,
      "en": "I just want to get this finished on time.",
      "cn": "我只是想按时完成这个。"
    },
    {
      "id": 30,
      "en": "I know, and I apologize for the delay, but some things were just beyond my control.",
      "cn": "我知道，我为延迟道歉，但有些事情超出了我的控制。"
    },
    {
      "id": 31,
      "en": "I had trouble booking the photographer, and then Michael was sick for three weeks, so I couldn't include him in the photos.",
      "cn": "我在预定摄影师时遇到麻烦，然后Michael生病了三周，所以我无法把他包括在照片中。"
    },
    {
      "id": 32,
      "en": "And the design team lost all the files, so I had to redo the pictures.",
      "cn": "而且设计团队丢失了所有文件，所以我不得不重新拍照。"
    },
    {
      "id": 33,
      "en": "I'm not going to put this off any longer, Casey.",
      "cn": "我不会再拖延了，Casey。"
    },
    {
      "id": 34,
      "en": "I want those photos ASAP.",
      "cn": "我想尽快要到那些照片。"
    },
    {
      "id": 35,
      "en": "All right, so Casey is in trouble, I think.",
      "cn": "好吧，我想Casey有麻烦了。"
    },
    {
      "id": 36,
      "en": "Yeah, I think her boss is pretty upset.",
      "cn": "是的，我觉得她的老板很生气。"
    },
    {
      "id": 37,
      "en": "Yeah.",
      "cn": "是的。"
    },
    {
      "id": 38,
      "en": "Well, let's take a look at some of the language that we saw in this dialogue in Language Takeaway.",
      "cn": "好吧，让我们看看在这个对话中看到的一些语言，语言要点。"
    },
    {
      "id": 39,
      "en": "Language Takeaway.",
      "cn": "语言要点。"
    },
    {
      "id": 40,
      "en": "First word today is deadline.",
      "cn": "今天的第一个词是截止日期。"
    },
    {
      "id": 41,
      "en": "Deadline.",
      "cn": "截止日期。"
    },
    {
      "id": 42,
      "en": "Deadline.",
      "cn": "截止日期。"
    },
    {
      "id": 43,
      "en": "Deadline.",
      "cn": "截止日期。"
    },
    {
      "id": 44,
      "en": "So, Erica, what's a deadline?",
      "cn": "所以，Erica，什么是截止日期？"
    },
    {
      "id": 45,
      "en": "It is the last possible date to do something.",
      "cn": "它是做某事的最后日期。"
    },
    {
      "id": 46,
      "en": "So, for example, when we were in school, our teacher would send us homework and say it was for Friday.",
      "cn": "例如，当我们在学校时，老师会给我们布置作业，并说是星期五。"
    },
    {
      "id": 47,
      "en": "So the deadline was Friday.",
      "cn": "所以截止日期是星期五。"
    },
    {
      "id": 48,
      "en": "Was Friday.",
      "cn": "是星期五。"
    },
    {
      "id": 49,
      "en": "Mm-hmm.",
      "cn": "嗯嗯。"
    },
    {
      "id": 50,
      "en": "Right?",
      "cn": "对吧？"
    },
    {
      "id": 51,
      "en": "Or when you're at work, you have projects that you have to finish by a certain date.",
      "cn": "或者当你在工作时，你有项目必须在某个日期之前完成。"
    },
    {
      "id": 52,
      "en": "That's your deadline.",
      "cn": "那就是你的截止日期。"
    },
    {
      "id": 53,
      "en": "Exactly.",
      "cn": "正确。"
    },
    {
      "id": 54,
      "en": "Okay, let's look at our next word.",
      "cn": "好的，让我们看看下一个词。"
    },
    {
      "id": 55,
      "en": "Extension.",
      "cn": "延期。"
    },
    {
      "id": 56,
      "en": "Extension.",
      "cn": "延期。"
    },
    {
      "id": 57,
      "en": "Extension.",
      "cn": "延期。"
    },
    {
      "id": 58,
      "en": "Extension.",
      "cn": "延期。"
    },
    {
      "id": 59,
      "en": "So, extension and deadline go together, right?",
      "cn": "所以，延期和截止日期是一起的，对吧？"
    },
    {
      "id": 60,
      "en": "Exactly.",
      "cn": "正确。"
    },
    {
      "id": 61,
      "en": "If you can't reach your deadline or you can't make your deadline, you must ask for an extension.",
      "cn": "如果你无法达到截止日期，或者无法按时完成，你必须请求延期。"
    },
    {
      "id": 62,
      "en": "An extension.",
      "cn": "延期。"
    },
    {
      "id": 63,
      "en": "So you ask for more time.",
      "cn": "所以你请求更多时间。"
    },
    {
      "id": 64,
      "en": "Yeah, an extension is moving the deadline in the future.",
      "cn": "是的，延期就是将截止日期推迟到未来。"
    },
    {
      "id": 65,
      "en": "All right, interesting.",
      "cn": "好吧，有趣。"
    },
    {
      "id": 66,
      "en": "Let's look at our next word.",
      "cn": "让我们看看下一个词。"
    },
    {
      "id": 67,
      "en": "Ran into.",
      "cn": "遇到。"
    },
    {
      "id": 68,
      "en": "Ran into.",
      "cn": "遇到。"
    },
    {
      "id": 69,
      "en": "Ran into.",
      "cn": "遇到。"
    },
    {
      "id": 70,
      "en": "Ran into some problems.",
      "cn": "遇到一些问题。"
    },
    {
      "id": 71,
      "en": "So we ran into some problems in this dialogue.",
      "cn": "所以我们在这个对话中遇到了一些问题。"
    },
    {
      "id": 72,
      "en": "Let's listen to some more examples of run into so we can understand the meaning.",
      "cn": "让我们听一些关于遇到的更多例子，以便理解其含义。"
    },
    {
      "id": 73,
      "en": "Example one.",
      "cn": "例子一。"
    },
    {
      "id": 74,
      "en": "We ran into a storm on our way home.",
      "cn": "我们在回家的路上遇到了一场暴风雨。"
    },
    {
      "id": 75,
      "en": "Example two.",
      "cn": "例子二。"
    },
    {
      "id": 76,
      "en": "If you're not careful now, you're going to run into a lot of problems later.",
      "cn": "如果你现在不小心，你将来会遇到很多问题。"
    },
    {
      "id": 77,
      "en": "Example three.",
      "cn": "例子三。"
    },
    {
      "id": 78,
      "en": "I ran into some trouble with my computer.",
      "cn": "我在电脑上遇到了一些麻烦。"
    },
    {
      "id": 79,
      "en": "Okay, good example.",
      "cn": "好的，很好的例子。"
    },
    {
      "id": 80,
      "en": "So it's clear now, right?",
      "cn": "所以现在很清楚了，对吧？"
    },
    {
      "id": 81,
      "en": "Right, if you run into problems, you meet some problems.",
      "cn": "对，如果你遇到问题，就是遇到了一些问题。"
    },
    {
      "id": 82,
      "en": "Right, many students say it in that way.",
      "cn": "对，很多学生这样说。"
    },
    {
      "id": 83,
      "en": "I met some problems.",
      "cn": "我遇到了一些问题。"
    },
    {
      "id": 84,
      "en": "Yeah, but that's wrong.",
      "cn": "是的，但那是错的。"
    },
    {
      "id": 85,
      "en": "Right, so you would say I ran into some problems.",
      "cn": "对，所以你应该说我遇到了一些问题。"
    },
    {
      "id": 86,
      "en": "Right, I met some problems is wrong, wrong, wrong.",
      "cn": "对，我遇到了一些问题是错的，错的，错的。"
    },
    {
      "id": 87,
      "en": "Okay, don't say met some problems.",
      "cn": "好的，不要说遇到一些问题。"
    },
    {
      "id": 88,
      "en": "I ran into some problems.",
      "cn": "我遇到了一些问题。"
    },
    {
      "id": 89,
      "en": "I ran into, okay.",
      "cn": "我遇到了，好的。"
    },
    {
      "id": 90,
      "en": "And our last word for language take away.",
      "cn": "我们的最后一个语言要点。"
    },
    {
      "id": 91,
      "en": "Delayed.",
      "cn": "延迟。"
    },
    {
      "id": 92,
      "en": "Delayed.",
      "cn": "延迟。"
    },
    {
      "id": 93,
      "en": "Delayed.",
      "cn": "延迟。"
    },
    {
      "id": 94,
      "en": "Delayed.",
      "cn": "延迟。"
    },
    {
      "id": 95,
      "en": "So when something is delayed, it's... Late.",
      "cn": "所以当某事被延迟时，它是... 晚的。"
    },
    {
      "id": 96,
      "en": "Late.",
      "cn": "晚的。"
    },
    {
      "id": 97,
      "en": "And the opposite is... On time.",
      "cn": "而相反的是... 按时。"
    },
    {
      "id": 98,
      "en": "Yeah, so your flight was delayed.",
      "cn": "是的，所以你的航班被延迟了。"
    },
    {
      "id": 99,
      "en": "Or your flight was on time.",
      "cn": "或者你的航班按时。"
    },
    {
      "id": 100,
      "en": "The project was delayed.",
      "cn": "项目被延迟了。"
    },
    {
      "id": 101,
      "en": "Or your project was on time.",
      "cn": "或者你的项目是准时的。"
    },
    {
      "id": 102,
      "en": "Clear.",
      "cn": "明白了。"
    },
    {
      "id": 103,
      "en": "Alright, so now let's go back to the dialogue.",
      "cn": "好的，现在我们回到对话。"
    },
    {
      "id": 104,
      "en": "Let's listen to it again.",
      "cn": "我们再听一遍。"
    },
    {
      "id": 105,
      "en": "And this time it will be a little bit slower so you can understand some of these phrases we just talked about.",
      "cn": "这次会慢一点，这样你可以理解我们刚才谈到的一些短语。"
    },
    {
      "id": 106,
      "en": "So, Casey, how are things going with the photos for the press kit?",
      "cn": "所以，Casey，新闻资料包的照片进展如何？"
    },
    {
      "id": 107,
      "en": "Yeah, I've been meaning to talk to you about that.",
      "cn": "是的，我一直想和你谈谈这个。"
    },
    {
      "id": 108,
      "en": "I might need to ask for an extension on that deadline.",
      "cn": "我可能需要请求延长截止日期。"
    },
    {
      "id": 109,
      "en": "You've had over a month to get this finalized.",
      "cn": "你已经有一个多月的时间来完成这个。"
    },
    {
      "id": 110,
      "en": "Why are things delayed?",
      "cn": "为什么会延误？"
    },
    {
      "id": 111,
      "en": "Well, the thing is, we ran into a lot of problems.",
      "cn": "嗯，问题是我们遇到了很多麻烦。"
    },
    {
      "id": 112,
      "en": "I'm not finished on time.",
      "cn": "我没有按时完成。"
    },
    {
      "id": 113,
      "en": "I know.",
      "cn": "我知道。"
    },
    {
      "id": 114,
      "en": "And I apologize for the delay.",
      "cn": "我为延误道歉。"
    },
    {
      "id": 115,
      "en": "But some things were just beyond my control.",
      "cn": "但有些事情超出了我的控制。"
    },
    {
      "id": 116,
      "en": "I had trouble booking the photographer.",
      "cn": "我在预定摄影师时遇到麻烦。"
    },
    {
      "id": 117,
      "en": "And then Michael was sick for three weeks so I couldn't include him in the photos.",
      "cn": "然后Michael病了三周，所以我无法把他包括在照片中。"
    },
    {
      "id": 118,
      "en": "And the design team lost all the files so I had to redo the pictures.",
      "cn": "设计团队丢失了所有文件，所以我不得不重新拍照。"
    },
    {
      "id": 119,
      "en": "I'm not going to put this off any longer, Casey.",
      "cn": "我不会再拖延了，Casey。"
    },
    {
      "id": 120,
      "en": "I want those photos ASAP.",
      "cn": "我想要那些照片，尽快。"
    },
    {
      "id": 121,
      "en": "Okay, so there were some really useful phrases that we saw in this dialogue.",
      "cn": "好的，我们在这个对话中看到了一些非常有用的短语。"
    },
    {
      "id": 122,
      "en": "Yeah, some wonderful phrases that you can use when you want to ask for more time.",
      "cn": "是的，有一些很棒的短语可以用来请求更多时间。"
    },
    {
      "id": 123,
      "en": "Okay, so let's look at these phrases in fluency builder.",
      "cn": "好的，让我们在流利度构建器中看看这些短语。"
    },
    {
      "id": 124,
      "en": "All right, what's our first phrase?",
      "cn": "好的，我们的第一个短语是什么？"
    },
    {
      "id": 125,
      "en": "I've been meaning to talk to you.",
      "cn": "我一直想和你谈谈。"
    },
    {
      "id": 126,
      "en": "I've been meaning to.",
      "cn": "我一直想这样做。"
    },
    {
      "id": 127,
      "en": "I've been meaning to.",
      "cn": "我一直想这样做。"
    },
    {
      "id": 128,
      "en": "Okay, we have some really great examples of how you can combine I've been meaning to with different verbs.",
      "cn": "好的，我们有一些很好的例子，展示了如何将“我一直想”与不同的动词结合。"
    },
    {
      "id": 129,
      "en": "Yeah, let's listen.",
      "cn": "是的，我们来听听。"
    },
    {
      "id": 130,
      "en": "Example one.",
      "cn": "示例一。"
    },
    {
      "id": 131,
      "en": "I'm sorry I haven't called you yet.",
      "cn": "对不起，我还没给你打电话。"
    },
    {
      "id": 132,
      "en": "I've been meaning to but I've been busy.",
      "cn": "我一直想打，但我一直很忙。"
    },
    {
      "id": 133,
      "en": "Example two.",
      "cn": "示例二。"
    },
    {
      "id": 134,
      "en": "I've been meaning to tell you but John quit yesterday.",
      "cn": "我一直想告诉你，但John昨天辞职了。"
    },
    {
      "id": 135,
      "en": "Example three.",
      "cn": "示例三。"
    },
    {
      "id": 136,
      "en": "I've been meaning to see that film for a while.",
      "cn": "我一直想看那部电影。"
    },
    {
      "id": 137,
      "en": "I've been meaning to go to that restaurant but I haven't had time.",
      "cn": "我一直想去那家餐厅，但我没有时间。"
    },
    {
      "id": 138,
      "en": "So you've been wanting to for a long time.",
      "cn": "所以你已经想了很久。"
    },
    {
      "id": 139,
      "en": "I've been thinking about it.",
      "cn": "我一直在考虑。"
    },
    {
      "id": 140,
      "en": "I've been planning to do it.",
      "cn": "我一直在计划去做。"
    },
    {
      "id": 141,
      "en": "But you just haven't done it.",
      "cn": "但你就是没有去做。"
    },
    {
      "id": 142,
      "en": "I haven't done it maybe because I haven't had time or money.",
      "cn": "我没有去做，可能是因为我没有时间或钱。"
    },
    {
      "id": 143,
      "en": "Okay, good phrase.",
      "cn": "好的，很好的短语。"
    },
    {
      "id": 144,
      "en": "Our next phrase is beyond my control.",
      "cn": "我们下一个短语是超出我的控制。"
    },
    {
      "id": 145,
      "en": "Beyond my control.",
      "cn": "超出我的控制。"
    },
    {
      "id": 146,
      "en": "It's beyond my control.",
      "cn": "这超出了我的控制。"
    },
    {
      "id": 147,
      "en": "So it means that I can't control it.",
      "cn": "所以这意味着我无法控制它。"
    },
    {
      "id": 148,
      "en": "You can't do anything about it.",
      "cn": "你对此无能为力。"
    },
    {
      "id": 149,
      "en": "Can't do anything about it.",
      "cn": "无能为力。"
    },
    {
      "id": 150,
      "en": "The weather is beyond my control.",
      "cn": "天气超出我的控制。"
    },
    {
      "id": 151,
      "en": "Right, or relate with this project because Jane was sick for one month.",
      "cn": "对，或者与这个项目有关，因为Jane病了一个月。"
    },
    {
      "id": 152,
      "en": "It was beyond my control.",
      "cn": "这超出了我的控制。"
    },
    {
      "id": 153,
      "en": "Okay, it wasn't your fault.",
      "cn": "好吧，这不是你的错。"
    },
    {
      "id": 154,
      "en": "No.",
      "cn": "不。"
    },
    {
      "id": 155,
      "en": "Okay, and our last phrase for fluency builder put this off.",
      "cn": "好的，我们流利度构建器的最后一个短语是拖延。"
    },
    {
      "id": 156,
      "en": "Put this off.",
      "cn": "拖延。"
    },
    {
      "id": 157,
      "en": "Put this off.",
      "cn": "拖延。"
    },
    {
      "id": 158,
      "en": "Put this off.",
      "cn": "拖延。"
    },
    {
      "id": 159,
      "en": "So let's listen to some more examples of put this off before we explain the meaning.",
      "cn": "所以在我们解释含义之前，让我们听一些关于拖延的更多例子。"
    },
    {
      "id": 160,
      "en": "Example one.",
      "cn": "示例一。"
    },
    {
      "id": 161,
      "en": "I've been putting off this project for a week and it's due tomorrow.",
      "cn": "我已经拖延这个项目一周了，明天到期。"
    },
    {
      "id": 162,
      "en": "Example two.",
      "cn": "示例二。"
    },
    {
      "id": 163,
      "en": "Can we put off our meeting until next week?",
      "cn": "我们可以把会议推迟到下周吗？"
    },
    {
      "id": 164,
      "en": "I'm too busy right now.",
      "cn": "我现在太忙了。"
    },
    {
      "id": 165,
      "en": "Example three.",
      "cn": "示例三。"
    },
    {
      "id": 166,
      "en": "I've been putting off my email all day and now I have 50 messages to respond to.",
      "cn": "我整天都在拖延我的电子邮件，现在我有50条消息要回复。"
    },
    {
      "id": 167,
      "en": "So Marco, when you put something off, you... Leave it for later.",
      "cn": "所以Marco，当你拖延某事时，你……把它留到以后。"
    },
    {
      "id": 168,
      "en": "Okay.",
      "cn": "好的。"
    },
    {
      "id": 169,
      "en": "Right, so maybe I have to write a report today.",
      "cn": "对，所以也许我今天必须写一份报告。"
    },
    {
      "id": 170,
      "en": "Mm-hmm.",
      "cn": "嗯嗯。"
    },
    {
      "id": 171,
      "en": "But I'm gonna put it off till tomorrow.",
      "cn": "但我会把它拖到明天。"
    },
    {
      "id": 172,
      "en": "So you're gonna do it tomorrow.",
      "cn": "所以你明天会做。"
    },
    {
      "id": 173,
      "en": "I'll do it tomorrow.",
      "cn": "我明天会做。"
    },
    {
      "id": 174,
      "en": "Okay, so we've seen some really great words and some really good phrases, so now let's listen to our dialogue for the last time and then we'll come back and talk some more.",
      "cn": "好的，我们看到了一些很好的单词和短语，现在让我们最后一次听我们的对话，然后我们再回来聊聊。"
    },
    {
      "id": 175,
      "en": "So, Casey, how are things going with the photos for the press kit?",
      "cn": "所以，Casey，新闻资料包的照片进展如何？"
    },
    {
      "id": 176,
      "en": "Yeah, I've been meaning to talk to you about that.",
      "cn": "是的，我一直想和你谈谈这个。"
    },
    {
      "id": 177,
      "en": "I might need to ask for an extension on that deadline.",
      "cn": "我可能需要请求延长截止日期。"
    },
    {
      "id": 178,
      "en": "You've had over a month to get this finalized.",
      "cn": "你已经有一个多月的时间来完成这个。"
    },
    {
      "id": 179,
      "en": "Why are things delayed?",
      "cn": "为什么会延误？"
    },
    {
      "id": 180,
      "en": "Well, the thing is we ran into a lot of problems.",
      "cn": "嗯，问题是我们遇到了很多麻烦。"
    },
    {
      "id": 181,
      "en": "I'm not looking for excuses here.",
      "cn": "我不是在找借口。"
    },
    {
      "id": 182,
      "en": "I just want to get this finished on time.",
      "cn": "我只是想按时完成。"
    },
    {
      "id": 183,
      "en": "I know, and I apologize for the delay, but some things were just beyond my control.",
      "cn": "我知道，我为延误道歉，但有些事情超出了我的控制。"
    },
    {
      "id": 184,
      "en": "I had trouble booking the photographer and then Michael was sick for three weeks, so I couldn't include him in the photos.",
      "cn": "我在预定摄影师时遇到麻烦，然后Michael病了三周，所以我无法把他包括在照片中。"
    },
    {
      "id": 185,
      "en": "And the design team lost all the files, so I had to redo the pictures.",
      "cn": "设计团队丢失了所有文件，所以我不得不重新拍照。"
    },
    {
      "id": 186,
      "en": "I'm not going to put this off any longer, Casey.",
      "cn": "我不会再拖延了，Casey。"
    },
    {
      "id": 187,
      "en": "I want those photos ASAP.",
      "cn": "我想要那些照片，尽快。"
    },
    {
      "id": 188,
      "en": "Well, Marco, do you think that Casey's reasons for being late are good?",
      "cn": "好吧，Marco，你认为Casey迟到的理由好吗？"
    },
    {
      "id": 189,
      "en": "I think so, because it wasn't really her fault, the whole situation with the photographer, and then one of her co-workers was sick for three weeks.",
      "cn": "我认为是的，因为这并不完全是她的错，摄影师的整个情况，然后她的一位同事病了三周。"
    },
    {
      "id": 190,
      "en": "It's not really her fault, right?",
      "cn": "这并不完全是她的错，对吧？"
    },
    {
      "id": 191,
      "en": "Right, but maybe the boss thinks that she's making excuses.",
      "cn": "对，但也许老板认为她在找借口。"
    },
    {
      "id": 192,
      "en": "Yeah, maybe she's making excuses.",
      "cn": "是的，也许她在找借口。"
    },
    {
      "id": 193,
      "en": "That's really common.",
      "cn": "这很常见。"
    },
    {
      "id": 194,
      "en": "Like, for example, when we were kids, you would say, oh, you know, my dog ate my homework.",
      "cn": "比如，当我们还是孩子的时候，你会说，哦，你知道，我的狗吃了我的作业。"
    },
    {
      "id": 195,
      "en": "Right, but that really happened to me once.",
      "cn": "对，但这真的发生在我身上。"
    },
    {
      "id": 196,
      "en": "Your dog ate your homework?",
      "cn": "你的狗吃了你的作业？"
    },
    {
      "id": 197,
      "en": "My cat ate my homework.",
      "cn": "我猫吃了我的作业。"
    },
    {
      "id": 198,
      "en": "Your cat ate your homework?",
      "cn": "你的猫吃了你的作业？"
    },
    {
      "id": 199,
      "en": "Yeah.",
      "cn": "是的。"
    },
    {
      "id": 200,
      "en": "And what did your teacher say?",
      "cn": "你的老师怎么说？"
    },
    {
      "id": 201,
      "en": "Well, actually, I was a really good student, so my teacher believed me.",
      "cn": "嗯，实际上，我是个很好的学生，所以老师相信我。"
    },
    {
      "id": 202,
      "en": "Well, my teacher wouldn't have believed me.",
      "cn": "嗯，我的老师不会相信我。"
    },
    {
      "id": 203,
      "en": "Really?",
      "cn": "真的？"
    },
    {
      "id": 204,
      "en": "No, no, she would have called my parents, most likely.",
      "cn": "不，不，她很可能会叫我的父母。"
    },
    {
      "id": 205,
      "en": "Well, my cat really did eat my homework, and I just left it on the table, and it chewed it all up.",
      "cn": "嗯，我的猫真的吃了我的作业，我只是把它放在桌子上，它把它咬坏了。"
    },
    {
      "id": 206,
      "en": "That's weird.",
      "cn": "这很奇怪。"
    },
    {
      "id": 207,
      "en": "Why would your cat do that?",
      "cn": "你的猫为什么要这样做？"
    },
    {
      "id": 208,
      "en": "I don't know.",
      "cn": "我不知道。"
    },
    {
      "id": 209,
      "en": "A lot of weird excuses out there.",
      "cn": "外面有很多奇怪的借口。"
    },
    {
      "id": 210,
      "en": "I was abducted by aliens.",
      "cn": "我被外星人绑架了。"
    },
    {
      "id": 211,
      "en": "My mom accidentally mailed my homework to Africa.",
      "cn": "我妈妈不小心把我的作业寄到了非洲。"
    },
    {
      "id": 212,
      "en": "Really?",
      "cn": "真的？"
    },
    {
      "id": 213,
      "en": "This happened to you?",
      "cn": "这发生在你身上？"
    },
    {
      "id": 214,
      "en": "Creative writing.",
      "cn": "创意写作。"
    },
    {
      "id": 215,
      "en": "Creative excuses.",
      "cn": "创意借口。"
    },
    {
      "id": 216,
      "en": "Well, I want to hear from our listeners.",
      "cn": "嗯，我想听听我们的听众。"
    },
    {
      "id": 217,
      "en": "I want to know what excuses they've used for being late with something.",
      "cn": "我想知道他们用什么借口来解释迟到。"
    },
    {
      "id": 218,
      "en": "So send us your excuses, send us your comments and questions, go to our website at EnglishPod.com, where Eric and I are always there to answer your questions.",
      "cn": "所以把你的借口发给我们，发送你的评论和问题，访问我们的网站 EnglishPod.com，埃里克和我总是在那里回答你的问题。"
    },
    {
      "id": 219,
      "en": "That's right, Marco, and this is an elementary lesson, right?",
      "cn": "没错，马尔科，这是一个初级课程，对吧？"
    },
    {
      "id": 220,
      "en": "Exactly.",
      "cn": "正是如此。"
    },
    {
      "id": 221,
      "en": "But we also have intermediate and upper intermediate and advanced lessons for you more fluent English speakers.",
      "cn": "但我们也有中级、高中级和高级课程，适合更流利的英语学习者。"
    },
    {
      "id": 222,
      "en": "Exactly, so if you're listening to us on iTunes, be sure to visit our website and come see what else we have to offer.",
      "cn": "没错，所以如果你在 iTunes 上收听我们，一定要访问我们的网站，看看我们还有什么其他内容。"
    },
    {
      "id": 223,
      "en": "Well, I think we're out of time, but until next time, it's goodbye!",
      "cn": "嗯，我想我们没时间了，但下次见，再见！"
    }
  ]
}